grf/__init__.py
grf/__main__.py
grf/config.py
grf/version.py
grf/request_handlers/__init__.py
grf/request_handlers/domain_records.py
grf/request_handlers/domains.py
godaddy_records_finder-0.1.2.dist-info/LICENSE.md
godaddy_records_finder-0.1.2.dist-info/METADATA
godaddy_records_finder-0.1.2.dist-info/WHEEL
godaddy_records_finder-0.1.2.dist-info/entry_points.txt
godaddy_records_finder-0.1.2.dist-info/top_level.txt
godaddy_records_finder-0.1.2.dist-info/RECORD
