Metadata-Version: 2.1
Name: godaddy-records-finder
Version: 0.1.2
Summary: GoDaddy Records Finder
Home-page: https://github.com/whodoneitagain/godaddy-records-finder
Author: whoDoneItAgain
Author-email: 12127434+whoDoneItAgain@users.noreply.github.com
Classifier: Development Status :: 4 - Beta
Classifier: Intended Audience :: Developers
Classifier: Natural Language :: English
Classifier: Operating System :: OS Independent
Classifier: Programming Language :: Python :: 3
Classifier: Programming Language :: Python :: 3.12
Classifier: Topic :: Internet :: Name Service (DNS)
Classifier: Topic :: Internet
Requires-Python: >=3.12, <=4.0, !=4.0
License-File: LICENSE.md
Requires-Dist: requests ==2.31.0
